CHANGELOG
COPYRIGHT
INSTALL
LICENSE
MANIFEST.in
Microsoft.VC90.CRT.manifest
README
catalan.nsh
english.nsh
french.nsh
german.nsh
neso.desktop
portuguese.nsh
setup.nsi
setup.py
slovenian.nsh
spanish.nsh
bin/neso
neso/__init__.py
neso.egg-info/PKG-INFO
neso.egg-info/SOURCES.txt
neso.egg-info/dependency_links.txt
neso.egg-info/not-zip-safe
neso.egg-info/requires.txt
neso.egg-info/top_level.txt
share/pixmaps/neso/neso-icon.svg
share/pixmaps/neso/neso.icns
share/pixmaps/neso/neso.ico